lunita/__init__.py
lunita/cliente.py
lunita/configuracion.py
lunita/constantes.py
lunita/historial.py
lunita/py.typed
lunita/sesion.py
lunita/sesion_asincrona.py
lunita/sesion_base.py
lunita/utils/__init__.py
lunita/utils/errores.py
lunita_mini-0.2.4.dist-info/licenses/LICENSE
lunita_mini-0.2.4.dist-info/METADATA
lunita_mini-0.2.4.dist-info/WHEEL
lunita_mini-0.2.4.dist-info/top_level.txt
lunita_mini-0.2.4.dist-info/RECORD
