Metadata-Version: 2.4
Name: lunita-mini
Version: 0.2.4
Summary: ¡Versión mini de Lunita!
Author-email: tuysh <angelmacloviomorales@gmail.com>
License: Copyright 2025 Tuysh
Project-URL: Homepage, https://github.com/Tuysh/lunita-mini/
Classifier: Programming Language :: Python :: 3
Classifier: License :: OSI Approved :: MIT License
Classifier: Operating System :: OS Independent
Classifier: Typing :: Typed
Requires-Python: >=3.10
License-File: LICENSE
Requires-Dist: groq>=1.0.0
Provides-Extra: test
Requires-Dist: pytest>=9.0.2; extra == "test"
Dynamic: license-file
